colorful_logger/__init__.py
colorful_logger/consts.py
colorful_logger/formatter.py
colorful_logger/handlers.py
colorful_logger/logger.py
colorful_logger/py.typed
colorful_logger/types.py
colorful_logger/version.py
colorful_logger-0.2.1.dist-info/licenses/LICENSE
colorful_logger-0.2.1.dist-info/METADATA
colorful_logger-0.2.1.dist-info/WHEEL
colorful_logger-0.2.1.dist-info/top_level.txt
colorful_logger-0.2.1.dist-info/RECORD
