Metadata-Version: 2.4
Name: colorful-logger
Version: 0.2.1
Summary: A colorful logger for python3.
Author-email: thep0y <thepoy@163.com>
License: MIT License
Project-URL: homepage, https://github.com/thep0y/python-logger
Project-URL: repository, https://github.com/thep0y/python-logger
Keywords: log,logger,logging,colorful
Classifier: Programming Language :: Python :: 3
Requires-Python: >=3
License-File: LICENSE
Requires-Dist: colort>=1.0.0
Requires-Dist: typing_extensions; python_version < "3.8"
Dynamic: license-file
